[{"name":"upasana","purchasedfood":[[{"name":"spring roll","quantity":"1","price":"2"}],[{"name":"spring roll","quantity":"1","price":"2"}],[{"name":"spring roll","quantity":"1","price":"2"}],[{"name":"spring roll","quantity":"1","price":"2"}],{"date":"uygygy","status":"not","purcase":[{"name":"spring roll","quantity":"1","price":"2"}]}]},{"name":"Saleela","purchasedfood":[{"date":"uygygy","status":"not","item":{"name":"Spaghetti and meatballs ","price":" 17","description":"traditional tomato sauce, basil, olive oil, pecorino cheese ","image":"images/grilled-branzino.jpg","foodId":"00"}},{"date":"uygygy","status":"not","item":{"name":"grilled artichoke ","price":" 12","description":"sea salt, truffle, grana padona cheese, lemon aioli","image":"images/grilled-artichoke.jpg","quan":"1","com":"cfdcv"}},{"date":"uygygy","status":"not","item":[{"name":"Spaghetti and meatballs ","description":"traditional tomato sauce, basil, olive oil, pecorino cheese ","price":" 17"},{"name":" Chicken pesto pasta ","description":"gigli pasta, toasted pine nut, garlic, basil, crispy caper ","price":" 17"}]}]}]